predicting_diabetes/__init__.py
predicting_diabetes-0.0.1.dist-info/LICENSE
predicting_diabetes-0.0.1.dist-info/METADATA
predicting_diabetes-0.0.1.dist-info/WHEEL
predicting_diabetes-0.0.1.dist-info/top_level.txt
predicting_diabetes-0.0.1.dist-info/RECORD
