Metadata-Version: 2.1
Name: predicting-diabetes
Version: 0.0.1
Summary: For Predicting Diabetes
Home-page: 
Author: Ritaj Zamel
Author-email: ritaj.zamel@gmail.com
Classifier: Programming Language :: Python :: 3
Classifier: License :: OSI Approved :: MIT License
Classifier: Operating System :: OS Independent
Requires-Python: >=3.7
License-File: LICENSE
